ab_bayes_test/__init__.py
ab_bayes_test/ab_bayestest.py
ab_bayes_test/inference/__init__.py
ab_bayes_test/inference/base_inference.py
ab_bayes_test/inference/conjugate_inference.py
ab_bayes_test/inference/mcmc_inference.py
ab_bayes_test/likelihoods/__init__.py
ab_bayes_test/likelihoods/likelihood.py
ab_bayes_test-0.1.0.dist-info/licenses/LICENSE
ab_bayes_test-0.1.0.dist-info/METADATA
ab_bayes_test-0.1.0.dist-info/WHEEL
ab_bayes_test-0.1.0.dist-info/top_level.txt
ab_bayes_test-0.1.0.dist-info/RECORD
